odoo10_addon_account_invoice_start_end_dates-10.0.1.0.0-py2.7-nspkg.pth
odoo10_addon_account_invoice_start_end_dates-10.0.1.0.0.dist-info/top_level.txt
odoo10_addon_account_invoice_start_end_dates-10.0.1.0.0.dist-info/WHEEL
odoo10_addon_account_invoice_start_end_dates-10.0.1.0.0.dist-info/RECORD
odoo10_addon_account_invoice_start_end_dates-10.0.1.0.0.dist-info/metadata.json
odoo10_addon_account_invoice_start_end_dates-10.0.1.0.0.dist-info/DESCRIPTION.rst
odoo10_addon_account_invoice_start_end_dates-10.0.1.0.0.dist-info/METADATA
odoo10_addon_account_invoice_start_end_dates-10.0.1.0.0.dist-info/namespace_packages.txt
odoo/addons/account_invoice_start_end_dates/__manifest__.py
odoo/addons/account_invoice_start_end_dates/__init__.py
odoo/addons/account_invoice_start_end_dates/README.rst
odoo/addons/account_invoice_start_end_dates/models/account_move_line.py
odoo/addons/account_invoice_start_end_dates/models/product.py
odoo/addons/account_invoice_start_end_dates/models/account_invoice.py
odoo/addons/account_invoice_start_end_dates/models/__init__.py
odoo/addons/account_invoice_start_end_dates/views/account_move.xml
odoo/addons/account_invoice_start_end_dates/views/account_invoice.xml
odoo/addons/account_invoice_start_end_dates/views/product.xml
odoo/addons/account_invoice_start_end_dates/tests/test_invoice_start_end_dates.py
odoo/addons/account_invoice_start_end_dates/tests/__init__.py
odoo/addons/account_invoice_start_end_dates/demo/product_demo.xml
